kck_utils/__init__.py
kck_utils-1.0.0.dist-info/METADATA
kck_utils-1.0.0.dist-info/WHEEL
kck_utils-1.0.0.dist-info/top_level.txt
kck_utils-1.0.0.dist-info/RECORD
